[
	{
		"tconst": "tt0000001",
		"titleType": "short",
		"primaryTitle": "Carmencita",
		"originalTitle": "Carmencita",
		"isAdult": 0,
		"startYear": 1894,
		"endYear": "\\N",
		"runtimeMinutes": 1,
		"genres": "Documentary,Short"
	},
	{
		"tconst": "tt0000002",
		"titleType": "short",
		"primaryTitle": "Le clown et ses chiens",
		"originalTitle": "Le clown et ses chiens",
		"isAdult": 0,
		"startYear": 1892,
		"endYear": "\\N",
		"runtimeMinutes": 5,
		"genres": "Animation,Short"
	},
	{
		"tconst": "tt0000003",
		"titleType": "short",
		"primaryTitle": "Pauvre Pierrot",
		"originalTitle": "Pauvre Pierrot",
		"isAdult": 0,
		"startYear": 1892,
		"endYear": "\\N",
		"runtimeMinutes": 4,
		"genres": "Animation,Comedy,Romance"
	},
	{
		"tconst": "tt0000004",
		"titleType": "short",
		"primaryTitle": "Un bon bock",
		"originalTitle": "Un bon bock",
		"isAdult": 0,
		"startYear": 1892,
		"endYear": "\\N",
		"runtimeMinutes": "\\N",
		"genres": "Animation,Short"
	},
	{
		"tconst": "tt0000005",
		"titleType": "short",
		"primaryTitle": "Blacksmith Scene",
		"originalTitle": "Blacksmith Scene",
		"isAdult": 0,
		"startYear": 1893,
		"endYear": "\\N",
		"runtimeMinutes": 1,
		"genres": "Comedy,Short"
	},
	{
		"tconst": "tt0000006",
		"titleType": "short",
		"primaryTitle": "Chinese Opium Den",
		"originalTitle": "Chinese Opium Den",
		"isAdult": 0,
		"startYear": 1894,
		"endYear": "\\N",
		"runtimeMinutes": 1,
		"genres": "Short"
	},
	{
		"tconst": "tt0000007",
		"titleType": "short",
		"primaryTitle": "Corbett and Courtney Before the Kinetograph",
		"originalTitle": "Corbett and Courtney Before the Kinetograph",
		"isAdult": 0,
		"startYear": 1894,
		"endYear": "\\N",
		"runtimeMinutes": 1,
		"genres": "Short,Sport"
	},
	{
		"tconst": "tt0000008",
		"titleType": "short",
		"primaryTitle": "Edison Kinetoscopic Record of a Sneeze",
		"originalTitle": "Edison Kinetoscopic Record of a Sneeze",
		"isAdult": 0,
		"startYear": 1894,
		"endYear": "\\N",
		"runtimeMinutes": 1,
		"genres": "Documentary,Short"
	},
	{
		"tconst": "tt0000009",
		"titleType": "movie",
		"primaryTitle": "Miss Jerry",
		"originalTitle": "Miss Jerry",
		"isAdult": 0,
		"startYear": 1894,
		"endYear": "\\N",
		"runtimeMinutes": 45,
		"genres": "Romance"
	},
	{
		"tconst": "tt0000010",
		"titleType": "short",
		"primaryTitle": "Exiting the Factory",
		"originalTitle": "La sortie de lusine Lumière à Lyon",
		"isAdult": 0,
		"startYear": 1895,
		"endYear": "\\N",
		"runtimeMinutes": 1,
		"genres": "Documentary,Short"
	},
	{
		"tconst": "tt0000011",
		"titleType": "short",
		"primaryTitle": "Akrobatisches Potpourri",
		"originalTitle": "Akrobatisches Potpourri",
		"isAdult": 0,
		"startYear": 1895,
		"endYear": "\\N",
		"runtimeMinutes": 1,
		"genres": "Documentary,Short"
	},
	{
		"tconst": "tt0000012",
		"titleType": "short",
		"primaryTitle": "The Arrival of a Train",
		"originalTitle": "Larrivée dun train à La Ciotat",
		"isAdult": 0,
		"startYear": 1896,
		"endYear": "\\N",
		"runtimeMinutes": 1,
		"genres": "Action,Documentary,Short"
	},
	{
		"tconst": "tt0000013",
		"titleType": "short",
		"primaryTitle": "The Photographical Congress Arrives in Lyon",
		"originalTitle": "Neuville-sur-Saône: Débarquement du congrès des photographes à Lyon",
		"isAdult": 0,
		"startYear": 1895,
		"endYear": "\\N",
		"runtimeMinutes": 1,
		"genres": "Documentary,Short"
	},
	{
		"tconst": "tt0000014",
		"titleType": "short",
		"primaryTitle": "The Sprinkler Sprinkled",
		"originalTitle": "Larroseur arrosé",
		"isAdult": 0,
		"startYear": 1895,
		"endYear": "\\N",
		"runtimeMinutes": 1,
		"genres": "Comedy,Short"
	},
	{
		"tconst": "tt0000015",
		"titleType": "short",
		"primaryTitle": "Autour dune cabine",
		"originalTitle": "Autour dune cabine",
		"isAdult": 0,
		"startYear": 1894,
		"endYear": "\\N",
		"runtimeMinutes": 2,
		"genres": "Animation,Short"
	},
	{
		"tconst": "tt0000016",
		"titleType": "short",
		"primaryTitle": "Barque sortant du port",
		"originalTitle": "Barque sortant du port",
		"isAdult": 0,
		"startYear": 1895,
		"endYear": "\\N",
		"runtimeMinutes": 1,
		"genres": "Documentary,Short"
	},
	{
		"tconst": "tt0000017",
		"titleType": "short",
		"primaryTitle": "Italienischer Bauerntanz",
		"originalTitle": "Italienischer Bauerntanz",
		"isAdult": 0,
		"startYear": 1895,
		"endYear": "\\N",
		"runtimeMinutes": 1,
		"genres": "Documentary,Short"
	},
	{
		"tconst": "tt0000018",
		"titleType": "short",
		"primaryTitle": "Das boxende Känguruh",
		"originalTitle": "Das boxende Känguruh",
		"isAdult": 0,
		"startYear": 1895,
		"endYear": "\\N",
		"runtimeMinutes": 1,
		"genres": "Short"
	},
	{
		"tconst": "tt0000019",
		"titleType": "short",
		"primaryTitle": "The Clown Barber",
		"originalTitle": "The Clown Barber",
		"isAdult": 0,
		"startYear": 1898,
		"endYear": "\\N",
		"runtimeMinutes": "\\N",
		"genres": "Comedy,Short"
	},
	{
		"tconst": "tt0000020",
		"titleType": "short",
		"primaryTitle": "The Derby 1895",
		"originalTitle": "The Derby 1895",
		"isAdult": 0,
		"startYear": 1895,
		"endYear": "\\N",
		"runtimeMinutes": 1,
		"genres": "Documentary,Short,Sport"
	},
	{
		"tconst": "tt0000022",
		"titleType": "short",
		"primaryTitle": "Blacksmith Scene",
		"originalTitle": "Les forgerons",
		"isAdult": 0,
		"startYear": 1895,
		"endYear": "\\N",
		"runtimeMinutes": 1,
		"genres": "Documentary,Short"
	},
	{
		"tconst": "tt0000023",
		"titleType": "short",
		"primaryTitle": "The Sea",
		"originalTitle": "Baignade en mer",
		"isAdult": 0,
		"startYear": 1895,
		"endYear": "\\N",
		"runtimeMinutes": 1,
		"genres": "Documentary,Short"
	},
	{
		"tconst": "tt0000024",
		"titleType": "short",
		"primaryTitle": "Opening of the Kiel Canal",
		"originalTitle": "Opening of the Kiel Canal",
		"isAdult": 0,
		"startYear": 1895,
		"endYear": "\\N",
		"runtimeMinutes": "\\N",
		"genres": "News,Short"
	},
	{
		"tconst": "tt0000025",
		"titleType": "short",
		"primaryTitle": "The Oxford and Cambridge University Boat Race",
		"originalTitle": "The Oxford and Cambridge University Boat Race",
		"isAdult": 0,
		"startYear": 1895,
		"endYear": "\\N",
		"runtimeMinutes": "\\N",
		"genres": "News,Short,Sport"
	},
	{
		"tconst": "tt0000026",
		"titleType": "short",
		"primaryTitle": "The Messers. Lumière at Cards",
		"originalTitle": "Partie décarté",
		"isAdult": 0,
		"startYear": 1896,
		"endYear": "\\N",
		"runtimeMinutes": 1,
		"genres": "Documentary,Short"
	},
	{
		"tconst": "tt0000027",
		"titleType": "short",
		"primaryTitle": "Cordeliers Square in Lyon",
		"originalTitle": "Place des Cordeliers à Lyon",
		"isAdult": 0,
		"startYear": 1895,
		"endYear": "\\N",
		"runtimeMinutes": 1,
		"genres": "Documentary,Short"
	},
	{
		"tconst": "tt0000028",
		"titleType": "short",
		"primaryTitle": "Fishing for Goldfish",
		"originalTitle": "La pêche aux poissons rouges",
		"isAdult": 0,
		"startYear": 1895,
		"endYear": "\\N",
		"runtimeMinutes": 1,
		"genres": "Documentary,Short"
	},
	{
		"tconst": "tt0000029",
		"titleType": "short",
		"primaryTitle": "Babys Dinner",
		"originalTitle": "Repas de bébé",
		"isAdult": 0,
		"startYear": 1895,
		"endYear": "\\N",
		"runtimeMinutes": 1,
		"genres": "Documentary,Short"
	},
	{
		"tconst": "tt0000030",
		"titleType": "short",
		"primaryTitle": "Rough Sea at Dover",
		"originalTitle": "Rough Sea at Dover",
		"isAdult": 0,
		"startYear": 1895,
		"endYear": "\\N",
		"runtimeMinutes": 1,
		"genres": "Documentary,Short"
	},
	{
		"tconst": "tt0000031",
		"titleType": "short",
		"primaryTitle": "Jumping the Blanket",
		"originalTitle": "Le saut à la couverture",
		"isAdult": 0,
		"startYear": 1895,
		"endYear": "\\N",
		"runtimeMinutes": 1,
		"genres": "Documentary,Short"
	},
	{
		"tconst": "tt0000032",
		"titleType": "short",
		"primaryTitle": "Die Serpentintänzerin",
		"originalTitle": "Die Serpentintänzerin",
		"isAdult": 0,
		"startYear": 1895,
		"endYear": "\\N",
		"runtimeMinutes": 1,
		"genres": "Short"
	},
	{
		"tconst": "tt0000033",
		"titleType": "short",
		"primaryTitle": "Trick Riding",
		"originalTitle": "La voltige",
		"isAdult": 0,
		"startYear": 1895,
		"endYear": "\\N",
		"runtimeMinutes": 1,
		"genres": "Comedy,Documentary,Short"
	},
	{
		"tconst": "tt0000034",
		"titleType": "short",
		"primaryTitle": "Arrivée dun train gare de Vincennes",
		"originalTitle": "Arrivée dun train gare de Vincennes",
		"isAdult": 0,
		"startYear": 1896,
		"endYear": "\\N",
		"runtimeMinutes": 1,
		"genres": "Documentary,Short"
	},
	{
		"tconst": "tt0000035",
		"titleType": "short",
		"primaryTitle": "Watering the Flowers",
		"originalTitle": "Larroseur",
		"isAdult": 0,
		"startYear": 1896,
		"endYear": "\\N",
		"runtimeMinutes": 1,
		"genres": "Comedy,Short"
	},
	{
		"tconst": "tt0000036",
		"titleType": "short",
		"primaryTitle": "Awakening of Rip",
		"originalTitle": "Awakening of Rip",
		"isAdult": 0,
		"startYear": 1896,
		"endYear": "\\N",
		"runtimeMinutes": 0,
		"genres": "Drama,Short"
	},
	{
		"tconst": "tt0000037",
		"titleType": "short",
		"primaryTitle": "Sea Bathing",
		"originalTitle": "Baignade en mer",
		"isAdult": 0,
		"startYear": 1896,
		"endYear": "\\N",
		"runtimeMinutes": 1,
		"genres": "Short"
	},
	{
		"tconst": "tt0000038",
		"titleType": "short",
		"primaryTitle": "The Ball Game",
		"originalTitle": "The Ball Game",
		"isAdult": 0,
		"startYear": 1898,
		"endYear": "\\N",
		"runtimeMinutes": "\\N",
		"genres": "Documentary,Short,Sport"
	},
	{
		"tconst": "tt0000039",
		"titleType": "short",
		"primaryTitle": "Barnet Horse Fair",
		"originalTitle": "Barnet Horse Fair",
		"isAdult": 0,
		"startYear": 1896,
		"endYear": "\\N",
		"runtimeMinutes": "\\N",
		"genres": "Short"
	},
	{
		"tconst": "tt0000040",
		"titleType": "short",
		"primaryTitle": "Barque sortant du port de Trouville",
		"originalTitle": "Barque sortant du port de Trouville",
		"isAdult": 0,
		"startYear": 1896,
		"endYear": "\\N",
		"runtimeMinutes": "\\N",
		"genres": "Documentary,Short"
	},
	{
		"tconst": "tt0000041",
		"titleType": "short",
		"primaryTitle": "Bataille de neige",
		"originalTitle": "Bataille de neige",
		"isAdult": 0,
		"startYear": 1897,
		"endYear": "\\N",
		"runtimeMinutes": 1,
		"genres": "Action,Comedy,Documentary"
	},
	{
		"tconst": "tt0000042",
		"titleType": "short",
		"primaryTitle": "Bateau-mouche sur la Seine",
		"originalTitle": "Bateau-mouche sur la Seine",
		"isAdult": 0,
		"startYear": 1896,
		"endYear": "\\N",
		"runtimeMinutes": "\\N",
		"genres": "Documentary,Short"
	},
	{
		"tconst": "tt0000043",
		"titleType": "short",
		"primaryTitle": "Batteuse à vapeur",
		"originalTitle": "Batteuse à vapeur",
		"isAdult": 0,
		"startYear": 1896,
		"endYear": "\\N",
		"runtimeMinutes": "\\N",
		"genres": "Documentary,Short"
	},
	{
		"tconst": "tt0000044",
		"titleType": "short",
		"primaryTitle": "Le bivouac",
		"originalTitle": "Le bivouac",
		"isAdult": 0,
		"startYear": 1896,
		"endYear": "\\N",
		"runtimeMinutes": 1,
		"genres": "Short"
	},
	{
		"tconst": "tt0000045",
		"titleType": "short",
		"primaryTitle": "Les blanchisseuses",
		"originalTitle": "Les blanchisseuses",
		"isAdult": 0,
		"startYear": 1896,
		"endYear": "\\N",
		"runtimeMinutes": "\\N",
		"genres": "Short"
	},
	{
		"tconst": "tt0000046",
		"titleType": "short",
		"primaryTitle": "Bois de Boulogne",
		"originalTitle": "Bois de Boulogne",
		"isAdult": 0,
		"startYear": 1896,
		"endYear": "\\N",
		"runtimeMinutes": "\\N",
		"genres": "Documentary,Short"
	},
	{
		"tconst": "tt0000047",
		"titleType": "short",
		"primaryTitle": "Boulevard des Italiens",
		"originalTitle": "Boulevard des Italiens",
		"isAdult": 0,
		"startYear": 1896,
		"endYear": "\\N",
		"runtimeMinutes": "\\N",
		"genres": "Documentary,Short"
	},
	{
		"tconst": "tt0000048",
		"titleType": "short",
		"primaryTitle": "The Boxing Kangaroo",
		"originalTitle": "The Boxing Kangaroo",
		"isAdult": 0,
		"startYear": 1896,
		"endYear": "\\N",
		"runtimeMinutes": "\\N",
		"genres": "Short"
	},
	{
		"tconst": "tt0000049",
		"titleType": "short",
		"primaryTitle": "Boxing Match; or, Glove Contest",
		"originalTitle": "Boxing Match; or, Glove Contest",
		"isAdult": 0,
		"startYear": 1896,
		"endYear": "\\N",
		"runtimeMinutes": "\\N",
		"genres": "Short,Sport"
	},
	{
		"tconst": "tt0000050",
		"titleType": "short",
		"primaryTitle": "Bébé et fillettes",
		"originalTitle": "Bébé et fillettes",
		"isAdult": 0,
		"startYear": 1896,
		"endYear": "\\N",
		"runtimeMinutes": "\\N",
		"genres": "Documentary,Short"
	},
	{
		"tconst": "tt0000051",
		"titleType": "short",
		"primaryTitle": "The Bohemian Encampment",
		"originalTitle": "Campement de bohémiens",
		"isAdult": 0,
		"startYear": 1896,
		"endYear": "\\N",
		"runtimeMinutes": "\\N",
		"genres": "Documentary,Short"
	},
	{
		"tconst": "tt0000052",
		"titleType": "short",
		"primaryTitle": "Carga de rurales",
		"originalTitle": "Carga de rurales",
		"isAdult": 0,
		"startYear": 1896,
		"endYear": "\\N",
		"runtimeMinutes": 1,
		"genres": "Documentary,Short"
	},
	{
		"tconst": "tt0000053",
		"titleType": "short",
		"primaryTitle": "A Chegada do Comboio Inaugural à Estação Central do Porto",
		"originalTitle": "A Chegada do Comboio Inaugural à Estação Central do Porto",
		"isAdult": 0,
		"startYear": 1897,
		"endYear": "\\N",
		"runtimeMinutes": "\\N",
		"genres": "Documentary,Short"
	},
	{
		"tconst": "tt0000054",
		"titleType": "short",
		"primaryTitle": "A Merry-Go-Round",
		"originalTitle": "Les chevaux de bois",
		"isAdult": 0,
		"startYear": 1896,
		"endYear": "\\N",
		"runtimeMinutes": "\\N",
		"genres": "Short"
	},
	{
		"tconst": "tt0000055",
		"titleType": "short",
		"primaryTitle": "Le chiffonnier",
		"originalTitle": "Le chiffonnier",
		"isAdult": 0,
		"startYear": 1896,
		"endYear": "\\N",
		"runtimeMinutes": "\\N",
		"genres": "Short"
	},
	{
		"tconst": "tt0000056",
		"titleType": "short",
		"primaryTitle": "Uma Corrida de Touros no Campo Pequeno",
		"originalTitle": "Uma Corrida de Touros no Campo Pequeno",
		"isAdult": 0,
		"startYear": 1896,
		"endYear": "\\N",
		"runtimeMinutes": "\\N",
		"genres": "Short"
	},
	{
		"tconst": "tt0000057",
		"titleType": "short",
		"primaryTitle": "Cortège de tzar allant à Versailles",
		"originalTitle": "Cortège de tzar allant à Versailles",
		"isAdult": 0,
		"startYear": 1896,
		"endYear": "\\N",
		"runtimeMinutes": "\\N",
		"genres": "Documentary,Short"
	},
	{
		"tconst": "tt0000058",
		"titleType": "short",
		"primaryTitle": "Cortège de tzar au Bois de Boulogne",
		"originalTitle": "Cortège de tzar au Bois de Boulogne",
		"isAdult": 0,
		"startYear": 1896,
		"endYear": "\\N",
		"runtimeMinutes": "\\N",
		"genres": "Documentary,Short"
	},
	{
		"tconst": "tt0000059",
		"titleType": "short",
		"primaryTitle": "Coronation of a Village Maiden",
		"originalTitle": "Couronnement de la rosière",
		"isAdult": 0,
		"startYear": 1896,
		"endYear": "\\N",
		"runtimeMinutes": "\\N",
		"genres": "Short"
	},
	{
		"tconst": "tt0000060",
		"titleType": "short",
		"primaryTitle": "Dancing Darkies",
		"originalTitle": "Dancing Darkies",
		"isAdult": 0,
		"startYear": 1896,
		"endYear": "\\N",
		"runtimeMinutes": "\\N",
		"genres": "Documentary,Short"
	},
	{
		"tconst": "tt0000061",
		"titleType": "short",
		"primaryTitle": "Dancing Girls",
		"originalTitle": "Dancing Girls",
		"isAdult": 0,
		"startYear": 1896,
		"endYear": "\\N",
		"runtimeMinutes": "\\N",
		"genres": "Short"
	},
	{
		"tconst": "tt0000062",
		"titleType": "short",
		"primaryTitle": "Danse serpentine",
		"originalTitle": "Danse serpentine",
		"isAdult": 0,
		"startYear": 1896,
		"endYear": "\\N",
		"runtimeMinutes": 1,
		"genres": "Short"
	},
	{
		"tconst": "tt0000063",
		"titleType": "short",
		"primaryTitle": "Dessinateur express",
		"originalTitle": "Dessinateur express",
		"isAdult": 0,
		"startYear": 1896,
		"endYear": "\\N",
		"runtimeMinutes": "\\N",
		"genres": "Short"
	},
	{
		"tconst": "tt0000064",
		"titleType": "short",
		"primaryTitle": "Dessinateur: Chamberlain",
		"originalTitle": "Dessinateur: Chamberlain",
		"isAdult": 0,
		"startYear": 1896,
		"endYear": "\\N",
		"runtimeMinutes": "\\N",
		"genres": "Short"
	},
	{
		"tconst": "tt0000065",
		"titleType": "short",
		"primaryTitle": "Dessinateur: Reine Victoria",
		"originalTitle": "Dessinateur: Reine Victoria",
		"isAdult": 0,
		"startYear": 1896,
		"endYear": "\\N",
		"runtimeMinutes": "\\N",
		"genres": "Short"
	},
	{
		"tconst": "tt0000066",
		"titleType": "short",
		"primaryTitle": "Dessinateur: Von Bismark",
		"originalTitle": "Dessinateur: Von Bismark",
		"isAdult": 0,
		"startYear": 1896,
		"endYear": "\\N",
		"runtimeMinutes": "\\N",
		"genres": "Short"
	},
	{
		"tconst": "tt0000067",
		"titleType": "short",
		"primaryTitle": "Conjurer Making Ten Hats in Sixty Seconds",
		"originalTitle": "Dix chapeaux en 60 secondes",
		"isAdult": 0,
		"startYear": 1896,
		"endYear": "\\N",
		"runtimeMinutes": "\\N",
		"genres": "Fantasy,Short"
	},
	{
		"tconst": "tt0000068",
		"titleType": "short",
		"primaryTitle": "Unloading the Boat",
		"originalTitle": "Déchargement de bateaux",
		"isAdult": 0,
		"startYear": 1896,
		"endYear": "\\N",
		"runtimeMinutes": "\\N",
		"genres": "Documentary,Short"
	},
	{
		"tconst": "tt0000069",
		"titleType": "short",
		"primaryTitle": "Post No Bills",
		"originalTitle": "Défense dafficher",
		"isAdult": 0,
		"startYear": 1896,
		"endYear": "\\N",
		"runtimeMinutes": 1,
		"genres": "Short"
	},
	{
		"tconst": "tt0000070",
		"titleType": "short",
		"primaryTitle": "Démolition dun mur",
		"originalTitle": "Démolition dun mur",
		"isAdult": 0,
		"startYear": 1896,
		"endYear": "\\N",
		"runtimeMinutes": 1,
		"genres": "Documentary,Short"
	},
	{
		"tconst": "tt0000071",
		"titleType": "short",
		"primaryTitle": "Automobiles Starting a Race",
		"originalTitle": "Départ des automobiles",
		"isAdult": 0,
		"startYear": 1896,
		"endYear": "\\N",
		"runtimeMinutes": "\\N",
		"genres": "Short,Sport"
	},
	{
		"tconst": "tt0000072",
		"titleType": "short",
		"primaryTitle": "Officers of French Army Leaving Service",
		"originalTitle": "Départ des officiers",
		"isAdult": 0,
		"startYear": 1896,
		"endYear": "\\N",
		"runtimeMinutes": "\\N",
		"genres": "Short"
	},
	{
		"tconst": "tt0000073",
		"titleType": "short",
		"primaryTitle": "Effets de mer sur les rochers",
		"originalTitle": "Effets de mer sur les rochers",
		"isAdult": 0,
		"startYear": 1896,
		"endYear": "\\N",
		"runtimeMinutes": "\\N",
		"genres": "Documentary,Short"
	},
	{
		"tconst": "tt0000074",
		"titleType": "short",
		"primaryTitle": "Enfants jouant sur la plage",
		"originalTitle": "Enfants jouant sur la plage",
		"isAdult": 0,
		"startYear": 1896,
		"endYear": "\\N",
		"runtimeMinutes": "\\N",
		"genres": "Documentary,Short"
	},
	{
		"tconst": "tt0000075",
		"titleType": "short",
		"primaryTitle": "The Conjuring of a Woman at the House of Robert Houdin",
		"originalTitle": "Escamotage dune dame au théâtre Robert Houdin",
		"isAdult": 0,
		"startYear": 1896,
		"endYear": "\\N",
		"runtimeMinutes": 1,
		"genres": "Horror,Short"
	},
	{
		"tconst": "tt0000076",
		"titleType": "short",
		"primaryTitle": "Exit of Rip and the Dwarf",
		"originalTitle": "Exit of Rip and the Dwarf",
		"isAdult": 0,
		"startYear": 1896,
		"endYear": "\\N",
		"runtimeMinutes": 1,
		"genres": "Drama,Short"
	},
	{
		"tconst": "tt0000077",
		"titleType": "short",
		"primaryTitle": "Le fakir, mystère indien",
		"originalTitle": "Le fakir, mystère indien",
		"isAdult": 0,
		"startYear": 1896,
		"endYear": "\\N",
		"runtimeMinutes": "\\N",
		"genres": "Short"
	},
	{
		"tconst": "tt0000078",
		"titleType": "short",
		"primaryTitle": "Feira de Gado na Corujeira",
		"originalTitle": "Feira de Gado na Corujeira",
		"isAdult": 0,
		"startYear": 1896,
		"endYear": "\\N",
		"runtimeMinutes": 1,
		"genres": "Documentary,Short"
	},
	{
		"tconst": "tt0000079",
		"titleType": "short",
		"primaryTitle": "La gare Saint-Lazare",
		"originalTitle": "La gare Saint-Lazare",
		"isAdult": 0,
		"startYear": 1896,
		"endYear": "\\N",
		"runtimeMinutes": "\\N",
		"genres": "Documentary,Short"
	},
	{
		"tconst": "tt0000080",
		"titleType": "short",
		"primaryTitle": "Grandes manoeuvres",
		"originalTitle": "Grandes manoeuvres",
		"isAdult": 0,
		"startYear": 1896,
		"endYear": "\\N",
		"runtimeMinutes": "\\N",
		"genres": "Documentary,Short"
	},
	{
		"tconst": "tt0000081",
		"titleType": "short",
		"primaryTitle": "Towing a Boat on the River",
		"originalTitle": "Les haleurs de bateaux",
		"isAdult": 0,
		"startYear": 1896,
		"endYear": "\\N",
		"runtimeMinutes": "\\N",
		"genres": "Documentary,Short"
	},
	{
		"tconst": "tt0000082",
		"titleType": "short",
		"primaryTitle": "A Hard Wash",
		"originalTitle": "A Hard Wash",
		"isAdult": 0,
		"startYear": 1896,
		"endYear": "\\N",
		"runtimeMinutes": "\\N",
		"genres": "Comedy,Short"
	},
	{
		"tconst": "tt0000083",
		"titleType": "short",
		"primaryTitle": "Les indiscrets",
		"originalTitle": "Les indiscrets",
		"isAdult": 0,
		"startYear": 1896,
		"endYear": "\\N",
		"runtimeMinutes": "\\N",
		"genres": "Short"
	},
	{
		"tconst": "tt0000084",
		"titleType": "short",
		"primaryTitle": "Les ivrognes",
		"originalTitle": "Les ivrognes",
		"isAdult": 0,
		"startYear": 1896,
		"endYear": "\\N",
		"runtimeMinutes": "\\N",
		"genres": "Short"
	},
	{
		"tconst": "tt0000085",
		"titleType": "short",
		"primaryTitle": "Gardener Burning Weeds",
		"originalTitle": "Jardinier brûlant des herbes",
		"isAdult": 0,
		"startYear": 1896,
		"endYear": "\\N",
		"runtimeMinutes": "\\N",
		"genres": "Short"
	},
	{
		"tconst": "tt0000086",
		"titleType": "short",
		"primaryTitle": "Beach and Pier at Trouville, 1st part",
		"originalTitle": "Jetée et plage de Trouville (1er partie)",
		"isAdult": 0,
		"startYear": 1896,
		"endYear": "\\N",
		"runtimeMinutes": "\\N",
		"genres": "Documentary,Short"
	},
	{
		"tconst": "tt0000087",
		"titleType": "short",
		"primaryTitle": "Beach and Pier at Trouville, 2nd part",
		"originalTitle": "Jetée et plage de Trouville (2e partie)",
		"isAdult": 0,
		"startYear": 1896,
		"endYear": "\\N",
		"runtimeMinutes": "\\N",
		"genres": "Documentary,Short"
	},
	{
		"tconst": "tt0000088",
		"titleType": "short",
		"primaryTitle": "Market Day",
		"originalTitle": "Jour de marché à Trouville",
		"isAdult": 0,
		"startYear": 1896,
		"endYear": "\\N",
		"runtimeMinutes": "\\N",
		"genres": "Documentary,Short"
	},
	{
		"tconst": "tt0000089",
		"titleType": "short",
		"primaryTitle": "Leaving Jerusalem by Railway",
		"originalTitle": "Départ de Jérusalem en chemin de fer",
		"isAdult": 0,
		"startYear": 1897,
		"endYear": "\\N",
		"runtimeMinutes": 1,
		"genres": "Documentary,Short"
	},
	{
		"tconst": "tt0000090",
		"titleType": "short",
		"primaryTitle": "Libération des territoriaux",
		"originalTitle": "Libération des territoriaux",
		"isAdult": 0,
		"startYear": 1896,
		"endYear": "\\N",
		"runtimeMinutes": "\\N",
		"genres": "Documentary,Short"
	},
	{
		"tconst": "tt0000091",
		"titleType": "short",
		"primaryTitle": "The House of the Devil",
		"originalTitle": "Le manoir du diable",
		"isAdult": 0,
		"startYear": 1896,
		"endYear": "\\N",
		"runtimeMinutes": 3,
		"genres": "Horror,Short"
	},
	{
		"tconst": "tt0000092",
		"titleType": "short",
		"primaryTitle": "Marée montante sur Brise-Larmes",
		"originalTitle": "Marée montante sur Brise-Larmes",
		"isAdult": 0,
		"startYear": 1896,
		"endYear": "\\N",
		"runtimeMinutes": "\\N",
		"genres": "Documentary,Short"
	},
	{
		"tconst": "tt0000093",
		"titleType": "short",
		"primaryTitle": "Melbourne",
		"originalTitle": "Melbourne",
		"isAdult": 0,
		"startYear": 1896,
		"endYear": "\\N",
		"runtimeMinutes": "\\N",
		"genres": "Documentary,Short"
	}
]